[
  {
    "latin": "adeo, adire, adivi(ii), aditus",
    "english": "to go up to, to approach",
    "audio": "https:totallyareallinktotheaudio"
  },
  {
    "latin": "arcesso, arcessere, arcessivi, arcessitus",
    "english": "to summon, to send for",
    "audio": "https:totallyareallinktotheaudio"
  },
  {
    "latin": "ars, artis, f.",
    "english": "art",
    "audio": "https:totallyareallinktotheaudio"
  },
  {
    "latin": "auris, auris, f.",
    "english": "ear",
    "audio": "https:totallyareallinktotheaudio"
  },
  {
    "latin": "colloco, collocare, collocavi, collocatus",
    "english": "to place, to put",
    "audio": "https:totallyareallinktotheaudio"
  },
  {
    "latin": "crudelis, crudelis, crudele",
    "english": "cruel",
    "audio": "https:totallyareallinktotheaudio"
  },
  {
    "latin": "denique",
    "english": "at last, finally",
    "audio": "https:totallyareallinktotheaudio"
  },
  {
    "latin": "despero, desperare, desperavi, desperatus",
    "english": "to despair",
    "audio": "https:totallyareallinktotheaudio"
  },
  {
    "latin": "doctus, docta, doctum",
    "english": "learned, clever",
    "audio": "https:totallyareallinktotheaudio"
  },
  {
    "latin": "domus, domus, f.",
    "english": "home",
    "audio": "https:totallyareallinktotheaudio"
  },
  {
    "latin": "infero, inferre, intuli, illatus",
    "english": "to bring in, to bring on",
    "audio": "https:totallyareallinktotheaudio"
  },
  {
    "latin": "irrumpo, irrumpere, irrupi, irruptus",
    "english": "to burst in",
    "audio": "https:totallyareallinktotheaudio"
  },
  {
    "latin": "latus, lata, latum",
    "english": "wide",
    "audio": "https:totallyareallinktotheaudio"
  },
  {
    "latin": "libero, liberare, liberavi, liberatus",
    "english": "to free, to set free",
    "audio": "https:totallyareallinktotheaudio"
  },
  {
    "latin": "luna, lunae, f.",
    "english": "moon",
    "audio": "https:totallyareallinktotheaudio"
  },
  {
    "latin": "mors, mortis, f.",
    "english": "death",
    "audio": "https:totallyareallinktotheaudio"
  },
  {
    "latin": "oculus, oculi, m.",
    "english": "eye",
    "audio": "https:totallyareallinktotheaudio"
  },
  {
    "latin": "persuadeo, persuadere, persuasi, persuasus (+ dative)",
    "english": "to persuade",
    "audio": "https:totallyareallinktotheaudio"
  },
  {
    "latin": "pessimus, pessima, pessimum",
    "english": "very bad, worst",
    "audio": "https:totallyareallinktotheaudio"
  },
  {
    "latin": "preces, precum, f. pl.",
    "english": "prayers",
    "audio": "https:totallyareallinktotheaudio"
  },
  {
    "latin": "relinquo, relinquere, reliqui, relictus",
    "english": "to leave",
    "audio": "https:totallyareallinktotheaudio"
  },
  {
    "latin": "remedium, remedi(i), n.",
    "english": "cure",
    "audio": "https:totallyareallinktotheaudio"
  },
  {
    "latin": "sermo, sermonis, m.",
    "english": "conversation",
    "audio": "https:totallyareallinktotheaudio"
  },
  {
    "latin": "sicut",
    "english": "like",
    "audio": "https:totallyareallinktotheaudio"
  },
  {
    "latin": "tam",
    "english": "so",
    "audio": "https:totallyareallinktotheaudio"
  },
  {
    "latin": "tempto, temptare, temptavi, temptatus",
    "english": "to try",
    "audio": "https:totallyareallinktotheaudio"
  },
  {
    "latin": "vulnus, vulneris, n.",
    "english": "wound",
    "audio": "https:totallyareallinktotheaudio"
  },
  {
    "latin": "unus, una, unum",
    "english": "one",
    "audio": "https:totallyareallinktotheaudio"
  },
  {
    "latin": "duo, duae, duo",
    "english": "two",
    "audio": "https:totallyareallinktotheaudio"
  },
  {
    "latin": "tres, tres, tria",
    "english": "three",
    "audio": "https:totallyareallinktotheaudio"
  },
  {
    "latin": "quattuor",
    "english": "four",
    "audio": "https:totallyareallinktotheaudio"
  },
  {
    "latin": "quinque",
    "english": "five",
    "audio": "https:totallyareallinktotheaudio"
  },
  {
    "latin": "sex",
    "english": "six",
    "audio": "https:totallyareallinktotheaudio"
  },
  {
    "latin": "septem",
    "english": "seven",
    "audio": "https:totallyareallinktotheaudio"
  },
  {
    "latin": "octo",
    "english": "eight",
    "audio": "https:totallyareallinktotheaudio"
  },
  {
    "latin": "novem",
    "english": "nine",
    "audio": "https:totallyareallinktotheaudio"
  },
  {
    "latin": "decem",
    "english": "ten",
    "audio": "https:totallyareallinktotheaudio"
  },
  {
    "latin": "viginti",
    "english": "twenty",
    "audio": "https:totallyareallinktotheaudio"
  },
  {
    "latin": "triginta",
    "english": "thirty",
    "audio": "https:totallyareallinktotheaudio"
  },
  {
    "latin": "quadraginta",
    "english": "forty",
    "audio": "https:totallyareallinktotheaudio"
  },
  {
    "latin": "quinquaginta",
    "english": "fifty",
    "audio": "https:totallyareallinktotheaudio"
  }
]